run_my_monitoring_dashboard/__init__.py
run_my_monitoring_dashboard/business_monitoring_app.py
run_my_monitoring_dashboard/model_monitoring_app.py
run_my_monitoring_dashboard/run_app.py
run_my_monitoring_dashboard/system_monitoring_app.py
run_my_monitoring_dashboard-0.0.8.dist-info/METADATA
run_my_monitoring_dashboard-0.0.8.dist-info/WHEEL
run_my_monitoring_dashboard-0.0.8.dist-info/entry_points.txt
run_my_monitoring_dashboard-0.0.8.dist-info/top_level.txt
run_my_monitoring_dashboard-0.0.8.dist-info/RECORD
